countf/__init__.py
countf/countdown.py
counts-0.9.0.dist-info/METADATA
counts-0.9.0.dist-info/WHEEL
counts-0.9.0.dist-info/top_level.txt
counts-0.9.0.dist-info/RECORD
