Metadata-Version: 2.1
Name: counts
Version: 0.9.0
Summary: A Python library for managing rent expiration countdowns
Home-page: https://github.com/Erickadikah/count
Author: Erick Adikah
Author-email: your.email@example.com
License: MIT
Classifier: Development Status :: 3 - Alpha
Classifier: Intended Audience :: Developers
Classifier: License :: OSI Approved :: MIT License
Classifier: Programming Language :: Python :: 3
Classifier: Programming Language :: Python :: 3.8
